wireencoder/__init__.py
wireencoder/encoder.py
wireencoder/exceptions.py
wireencoder/zlib_b64.py
wireencoder/zlib_b85.py
wireencoder/zstd_b64.py
wire_encoder-1.0.4.dist-info/LICENSE
wire_encoder-1.0.4.dist-info/METADATA
wire_encoder-1.0.4.dist-info/WHEEL
wire_encoder-1.0.4.dist-info/top_level.txt
wire_encoder-1.0.4.dist-info/RECORD
