Metadata-Version: 2.1
Name: wire-encoder
Version: 1.0.4
Summary: A set of wire safe encoders
Home-page: http://gitlab.com/MimicOctopus/wireencoder
Author: Max Paradis
Author-email: max@nullptrsolutions.ca
License: MIT (see LICENSE)
Platform: UNKNOWN
Classifier: Environment :: Web Environment
Classifier: Intended Audience :: Developers
Classifier: License :: OSI Approved :: MIT License
Classifier: Programming Language :: Python :: 3
Classifier: Programming Language :: Python :: 3.5
Classifier: Programming Language :: Python :: 3.6
Classifier: Programming Language :: Python :: 3.7
Requires-Dist: pybase64 (==0.2.1)
Requires-Dist: zstandard (>=0.8.1)
